pythonmc/__init__.py
pythonmc/py.typed
pythonmc/block/__init__.py
pythonmc/block/block.py
pythonmc/block/block_pos.py
pythonmc/block/block_state.py
pythonmc/block/blocks.py
pythonmc/entity/__init__.py
pythonmc/entity/arm.py
pythonmc/entity/damage_sources.py
pythonmc/entity/entities.py
pythonmc/entity/entity.py
pythonmc/entity/hand.py
pythonmc/entity/living_entity.py
pythonmc/entity/removal_reasons.py
pythonmc/entity/effects/__init__.py
pythonmc/entity/effects/status_effect_instance.py
pythonmc/entity/effects/status_effects.py
pythonmc/item/__init__.py
pythonmc/item/hide_flags.py
pythonmc/item/item.py
pythonmc/item/item_rarity.py
pythonmc/item/item_stack.py
pythonmc/item/items.py
pythonmc/item/enchantment/__init__.py
pythonmc/item/enchantment/enchantment.py
pythonmc/item/enchantment/enchantment_rarity.py
pythonmc/item/enchantment/enchantments.py
pythonmc/player/__init__.py
pythonmc/player/ender_chest_inventory.py
pythonmc/player/hunger_manager.py
pythonmc/player/player_entity.py
pythonmc/player/player_inventory.py
pythonmc/player/player_manager.py
pythonmc/scoreboard/__init__.py
pythonmc/scoreboard/render_types.py
pythonmc/scoreboard/scoreboard.py
pythonmc/scoreboard/scoreboard_criterions.py
pythonmc/scoreboard/scoreboard_objective.py
pythonmc/scoreboard/scoreboard_player_score.py
pythonmc/scoreboard/team.py
pythonmc/scoreboard/rules/__init__.py
pythonmc/scoreboard/rules/collision_rules.py
pythonmc/scoreboard/rules/visibility_rules.py
pythonmc/server/__init__.py
pythonmc/server/server.py
pythonmc/server/difficulty/__init__.py
pythonmc/server/difficulty/difficulties.py
pythonmc/server/difficulty/difficulty.py
pythonmc/server/gamemode/__init__.py
pythonmc/server/gamemode/game_mode.py
pythonmc/server/gamemode/game_modes.py
pythonmc/server/text/__init__.py
pythonmc/server/text/formatting.py
pythonmc/server/text/text.py
pythonmc/world/__init__.py
pythonmc/world/executor.py
pythonmc/world/particles.py
pythonmc/world/time_.py
pythonmc/world/weather.py
pythonmc-1.0.5.dist-info/METADATA
pythonmc-1.0.5.dist-info/WHEEL
pythonmc-1.0.5.dist-info/top_level.txt
pythonmc-1.0.5.dist-info/RECORD
