Metadata-Version: 2.1
Name: pythonmc
Version: 1.0.5
Summary: The python library for PythonMC
Home-page: https://github.com/RevolvingMadness/PythonMC
Author: RevolvingMadness
Author-email: revolvingmad@gmail.com
Project-URL: Bug Tracker, https://github.com/RevolvingMadness/PythonMC/issues
Classifier: Programming Language :: Python :: 3
Classifier: License :: OSI Approved :: MIT License
Classifier: Operating System :: OS Independent
Requires-Python: >=3.9
